{
  "$schema": "https://json-schema.org/draft/2020-12/schema",
  "$id": "l9://resolver/resolver-capabilities/v1",
  "title": "L9 Resolver Capabilities",
  "type": "object",
  "additionalProperties": false,
  "required": [
    "schema_version",
    "phase",
    "capabilities",
    "limitations"
  ],
  "properties": {
    "schema_version": {
      "const": "l9.resolver-capabilities/v1"
    },
    "phase": {
      "const": "RESOLVER-P0"
    },
    "capabilities": {
      "type": "object"
    },
    "limitations": {
      "type": "array",
      "items": {
        "type": "string"
      }
    }
  }
}
